varibase/__init__.py
varibase/varibase.py
varibase-0.1.0.dist-info/METADATA
varibase-0.1.0.dist-info/WHEEL
varibase-0.1.0.dist-info/RECORD
