Metadata-Version: 2.1
Name: varibase
Version: 0.1.0
Summary: Varibase: Effortlessly save and retrieve Jupyter notebook variables to prevent data loss on crashes or restarts.
License: MIT
Keywords: jupyter,notebooks,variables,pickling,data-storage,persistent-storage,duckdb,data-recovery
Author: chandramohan
Author-email: chandramohansnayak@gmail.com
Requires-Python: >=3.9,<3.11
Classifier: License :: OSI Approved :: MIT License
Classifier: Programming Language :: Python :: 3
Classifier: Programming Language :: Python :: 3.9
Classifier: Programming Language :: Python :: 3.10
Requires-Dist: duckdb (>=1.1.3,<2.0.0)
Project-URL: Documentation, https://github.com/Chandramohan-97/varibase-docs.git
